bdfparser/__init__.py
bdfparser/bdfparser.py
bdfparser-2.2.0.dist-info/LICENSE
bdfparser-2.2.0.dist-info/METADATA
bdfparser-2.2.0.dist-info/WHEEL
bdfparser-2.2.0.dist-info/top_level.txt
bdfparser-2.2.0.dist-info/RECORD
