Metadata-Version: 2.1
Name: bdfparser
Version: 2.2.0
Summary: BDF (Glyph Bitmap Distribution Format) Bitmap Font File Parser in Python
Home-page: https://github.com/tomchen/bdfparser
Author: Tom Chen
Author-email: tomchen.org@gmail.com
License: UNKNOWN
Project-URL: Documentation, https://github.com/tomchen/bdfparser
Project-URL: Bug Reports, https://github.com/tomchen/bdfparser/issues
Project-URL: Source Code, https://github.com/tomchen/bdfparser
Keywords: bdf,bitmap,font,parser
Platform: UNKNOWN
Classifier: Development Status :: 5 - Production/Stable
Classifier: Intended Audience :: Developers
Classifier: Topic :: Software Development :: Build Tools
Classifier: Programming Language :: Python :: 3
Classifier: Programming Language :: Python :: 3.5
Classifier: Programming Language :: Python :: 3.6
Classifier: Programming Language :: Python :: 3.7
Classifier: Programming Language :: Python :: 3.8
Classifier: Programming Language :: Python :: 3.9
Classifier: Programming Language :: Python :: 3 :: Only
Classifier: License :: OSI Approved :: MIT License
Classifier: Operating System :: OS Independent
Requires-Python: >=3.5
Provides-Extra: dev
Requires-Dist: check-manifest ; extra == 'dev'
